contextapp/__init__.py
contextapp/context.py
contextapp/static/css/local.css
contextapp/static/images/albums-outline.svg
contextapp/static/images/chevron-back-outline.svg
contextapp/static/images/chevron-down-outline.svg
contextapp/static/images/chevron-end-outline.svg
contextapp/static/images/chevron-forward-outline.svg
contextapp/static/images/chevron-start-outline.svg
contextapp/static/images/chevron-up-outline.svg
contextapp/static/images/close-circle-outline.svg
contextapp/static/images/easel-outline.svg
contextapp/static/images/favicon.ico
contextapp/static/images/list-outline.svg
contextapp/static/images/logo.svg
contextapp/static/images/options-outline.svg
contextapp/static/images/settings-outline.svg
contextapp/templates/context-concordanceplot.html
contextapp/templates/context-default.html
contextapp/templates/context-nocorpus.html
contextapp/templates/context-query.html
contextapp/templates/context-template.html
contextapp/templates/corpus-info.html
contextapp/templates/detail.html
contextapp/templates/form-search.html
contextapp/templates/index.html
contextapp/templates/report-settings.html
contextapp/templates/settings.html
contextapp/templates/text.html
contextapp-0.1.5.dist-info/licenses/LICENSE
contextapp-0.1.5.dist-info/METADATA
contextapp-0.1.5.dist-info/WHEEL
contextapp-0.1.5.dist-info/entry_points.txt
contextapp-0.1.5.dist-info/top_level.txt
contextapp-0.1.5.dist-info/RECORD
