Metadata-Version: 2.4
Name: contextapp
Version: 0.1.5
Summary: A browser-based concordancer and language analysis application. 
Home-page: https://github.com/polsci/ConText
Author: Geoff Ford
Author-email: geoffrey.ford@canterbury.ac.nz
Requires-Python: >=3.11
License-File: LICENSE
Requires-Dist: conc
Requires-Dist: Flask
Requires-Dist: Flask-WTF
Requires-Dist: nh3
Requires-Dist: flaskwebgui
Dynamic: author
Dynamic: author-email
Dynamic: description
Dynamic: description-content-type
Dynamic: home-page
Dynamic: license-file
Dynamic: requires-dist
Dynamic: requires-python
Dynamic: summary
